operation_excel_mcp/charts.py
operation_excel_mcp/exceptions.py
operation_excel_mcp/pivot.py
operation_excel_mcp/ranges.py
operation_excel_mcp/server.py
operation_excel_mcp/sheets.py
operation_excel_mcp/workbook.py
operation_excel_mcp-0.1.1.dist-info/METADATA
operation_excel_mcp-0.1.1.dist-info/WHEEL
operation_excel_mcp-0.1.1.dist-info/entry_points.txt
operation_excel_mcp-0.1.1.dist-info/RECORD
