Metadata-Version: 2.4
Name: operation-excel-mcp
Version: 0.1.1
Summary: A library for reading and writing Microsoft Excel files
Requires-Python: >=3.13
Requires-Dist: xlwings>=0.30.0
